goodvirus/__about__.py
goodvirus/__init__.py
goodvirus/changelog.json
goodvirus/observer.py
goodvirus/update_check.py
goodvirus/version.txt
goodvirus/config/daemon_config.ini
goodvirus/core/__init__.py
goodvirus/core/memory_handler.py
goodvirus/core/update_popup.py
goodvirus/core/virus_detection.py
goodvirus-1.3.0.dist-info/LICENSE
goodvirus-1.3.0.dist-info/METADATA
goodvirus-1.3.0.dist-info/WHEEL
goodvirus-1.3.0.dist-info/entry_points.txt
goodvirus-1.3.0.dist-info/top_level.txt
goodvirus-1.3.0.dist-info/RECORD
