Metadata-Version: 2.1
Name: goodvirus
Version: 1.3.0
Summary: An ethical, self-updating system watchdog daemon with full-system scanning.
Home-page: https://pypi.org/project/goodvirus/
Author: Nico
Author-email: goodvirus.project@proton.me
License: MIT
Classifier: Development Status :: 4 - Beta
Classifier: Intended Audience :: End Users/Desktop
Classifier: Topic :: Security
Classifier: License :: OSI Approved :: MIT License
Classifier: Programming Language :: Python :: 3
Classifier: Operating System :: OS Independent
Requires-Python: >=3.7
License-File: LICENSE
Requires-Dist: psutil
Requires-Dist: configparser
